vizdoom/OpenAL32.dll
vizdoom/__init__.py
vizdoom/bots.cfg
vizdoom/freedoom2.wad
vizdoom/libmpg123-0.dll
vizdoom/libsndfile-1.dll
vizdoom/vizdoom.cp311-win_amd64.pyd
vizdoom/vizdoom.exe
vizdoom/vizdoom.pk3
vizdoom/gym_wrapper/__init__.py
vizdoom/gym_wrapper/base_gym_env.py
vizdoom/gym_wrapper/gym_env_defns.py
vizdoom/gymnasium_wrapper/__init__.py
vizdoom/gymnasium_wrapper/base_gymnasium_env.py
vizdoom/gymnasium_wrapper/gymnasium_env_defns.py
vizdoom/scenarios/README.md
vizdoom/scenarios/basic.cfg
vizdoom/scenarios/basic.wad
vizdoom/scenarios/cig.cfg
vizdoom/scenarios/cig.wad
vizdoom/scenarios/cig_with_unknown.wad
vizdoom/scenarios/deadly_corridor.cfg
vizdoom/scenarios/deadly_corridor.wad
vizdoom/scenarios/deathmatch.cfg
vizdoom/scenarios/deathmatch.wad
vizdoom/scenarios/defend_the_center.cfg
vizdoom/scenarios/defend_the_center.wad
vizdoom/scenarios/defend_the_line.cfg
vizdoom/scenarios/defend_the_line.wad
vizdoom/scenarios/health_gathering.cfg
vizdoom/scenarios/health_gathering.wad
vizdoom/scenarios/health_gathering_supreme.cfg
vizdoom/scenarios/health_gathering_supreme.wad
vizdoom/scenarios/learning.cfg
vizdoom/scenarios/multi.cfg
vizdoom/scenarios/multi_deathmatch.wad
vizdoom/scenarios/multi_duel.cfg
vizdoom/scenarios/multi_duel.wad
vizdoom/scenarios/my_way_home.cfg
vizdoom/scenarios/my_way_home.wad
vizdoom/scenarios/oblige.cfg
vizdoom/scenarios/predict_position.cfg
vizdoom/scenarios/predict_position.wad
vizdoom/scenarios/rocket_basic.cfg
vizdoom/scenarios/rocket_basic.wad
vizdoom/scenarios/simpler_basic.cfg
vizdoom/scenarios/simpler_basic.wad
vizdoom/scenarios/take_cover.cfg
vizdoom/scenarios/take_cover.wad
vizdoom-1.2.4.dist-info/METADATA
vizdoom-1.2.4.dist-info/WHEEL
vizdoom-1.2.4.dist-info/top_level.txt
vizdoom-1.2.4.dist-info/RECORD
