Metadata-Version: 2.1
Name: vizdoom
Version: 1.2.4
Summary: ViZDoom is Doom-based AI Research Platform for Reinforcement Learning from Raw Visual Information.
Home-page: https://vizdoom.farama.org
Author: Marek Wydmuch, Michał Kempka, Wojciech Jaśkowski, Farama Foundation, and the respective contributors
Author-email: mwydmuch@cs.put.poznan.pl
Keywords: vizdoom,doom,ai,deep learning,reinforcement learning,research
Platform: Linux
Platform: Mac OS X
Platform: Windows
Classifier: Development Status :: 5 - Production/Stable
Classifier: Intended Audience :: Education
Classifier: Intended Audience :: Science/Research
Classifier: Topic :: Scientific/Engineering :: Artificial Intelligence
Classifier: License :: OSI Approved :: MIT License
Classifier: Programming Language :: C++
Classifier: Programming Language :: Python :: 3
Classifier: Programming Language :: Python :: 3.8
Classifier: Programming Language :: Python :: 3.9
Classifier: Programming Language :: Python :: 3.10
Classifier: Programming Language :: Python :: 3.11
Classifier: Programming Language :: Python :: 3.12
Classifier: Operating System :: Microsoft :: Windows
Classifier: Operating System :: MacOS :: MacOS X
Classifier: Operating System :: POSIX :: Linux
Requires-Python: >=3.8.0,<3.13
Requires-Dist: numpy
Requires-Dist: gymnasium>=0.28.0
Requires-Dist: pygame>=2.1.3
Provides-Extra: gym
Requires-Dist: gym>=0.26.0; extra == "gym"
Requires-Dist: pygame>=2.1.3; extra == "gym"
Provides-Extra: test
Requires-Dist: pytest; extra == "test"
Requires-Dist: psutil; extra == "test"
